gaode/__init__.py
gaode/client.py
gaode-0.1.0.dist-info/METADATA
gaode-0.1.0.dist-info/WHEEL
gaode-0.1.0.dist-info/top_level.txt
gaode-0.1.0.dist-info/RECORD
