Metadata-Version: 2.1
Name: gaode
Version: 0.1.0
Summary: Gaode Python SDK.
Home-page: https://github.com/iamsk/gaode
Author: Bin
Author-email: iamsk.info@gmail.com
License: MIT
Platform: UNKNOWN
Classifier: License :: OSI Approved :: MIT License
Classifier: Programming Language :: Python
Classifier: Programming Language :: Python :: 3
Classifier: Programming Language :: Python :: 3.6
Classifier: Programming Language :: Python :: Implementation :: CPython
Classifier: Programming Language :: Python :: Implementation :: PyPy
Requires-Python: >=3.6.0
Requires-Dist: requests (>=2.19.1)
Requires-Dist: pytest (>=3.6.4)
